{
  "key_points": [
    "台股在四萬點關前震盪，市場關注輝達（Nvidia）財報前的走勢。",
    "被動元件族群受惠 AI 伺服器與低軌衛星需求，出現法人回補與擴散效應。",
    "SpaceX IPO 題材引發低軌衛星族群熱度，市場重心轉向實質營收與毛利。",
    "玻璃基板 (TGV) 成為先進封裝新寵，相關設備商獲大戶鎖碼。",
    "機器人族群受電腦展（COMPUTEX）預期帶動，資金提早布局。"
  ],
  "macro_outlook": [
    "10年期美債殖利率創15個月新高，油價受中東局勢影響走強，引發市場對通膨與殺盤的擔憂。",
    "專家認為此波動為「飆漲前的大買點」，高債息環境下資金會尋找具備實質獲利支撐的標的。",
    "輝達財報將是 AI 族群能否止跌回穩並引領大盤衝關的核心指標。"
  ],
  "targets": [
    {
      "code": "2327",
      "name": "國巨",
      "view": "多",
      "rationale": "AI 伺服器電容規格提升，帶動漲價題材與法人強勢回補。"
    },
    {
      "code": "3026",
      "name": "禾伸堂",
      "view": "多",
      "rationale": "被動元件擴散標的，具備漲價題材且股價相對基期較低。"
    },
    {
      "code": "2492",
      "name": "華新科",
      "view": "多",
      "rationale": "族群領頭羊，近期表現強悍，法人買盤支撐。"
    },
    {
      "code": "6285",
      "name": "啟碁",
      "view": "多",
      "rationale": "低軌衛星地面設備需求放量，營收獲利可驗證，股價創歷史新高。"
    },
    {
      "code": "4916",
      "name": "事欣科",
      "view": "多",
      "rationale": "具備航太與國防雙題材，受 SpaceX IPO 利多刺激，強勢拉出漲停。"
    },
    {
      "code": "6207",
      "name": "雷科",
      "view": "多",
      "rationale": "玻璃基板新題材設備廠，大戶鎖碼名單，具備技術突破優勢。"
    },
    {
      "code": "3491",
      "name": "昇達科",
      "view": "多",
      "rationale": "低軌衛星關鍵零組件，產品組合優化帶動毛利率顯著提升。"
    }
  ],
  "risk_factors": [
    "債息持續飆高可能對高估值科技股產生估值修正壓力。",
    "低軌衛星族群個別差異大，應避開僅有故事而無實質營收的公司。",
    "輝達財報若未能超預期，可能導致 AI 鏈短線出現較大幅度獲利了結賣壓。"
  ],
  "quotes": "油價跟債息飆升，其實是給投資人一個『右下角』切入的機會；被動元件這次是玩真的！"
}